README.txt
setup.py
hjjp/__init__.py
hjjp/hjjp.py
hjjp/hjjp_jiu.py
hjjp/hjjp_no-cookie.py
hjjp/hjjp_no_function.py
hjjp/hjjp_noselector.py
hjjp/xpath_test.py
hjjpcj.egg-info/PKG-INFO
hjjpcj.egg-info/SOURCES.txt
hjjpcj.egg-info/dependency_links.txt
hjjpcj.egg-info/entry_points.txt
hjjpcj.egg-info/top_level.txt