Metadata-Version: 1.0
Name: hjjpcj
Version: 0.9.8.6
Summary: hujiang dictionary
Home-page: https://github.com/Asutorufa/hujiang-japanese-dict
Author: Asutorufa
Author-email: pip@just2hide.anyalias.com
License: MIT Licence
Keywords: japanese dict dictionary hujiang
Platform: any
